setup.py
itsmatrix_cipher/__init__.py
itsmatrix_cipher.egg-info/PKG-INFO
itsmatrix_cipher.egg-info/SOURCES.txt
itsmatrix_cipher.egg-info/dependency_links.txt
itsmatrix_cipher.egg-info/top_level.txt