Metadata-Version: 2.1
Name: itsmatrix-cipher
Version: 0.0.1
Summary: Simple script cipher
Author: Its-MatriX
Requires: itsmatrix_cipher
